MANIFEST.in
README.md
setup.py
RoundCreator/CommandLine.py
RoundCreator/RoundCreator.py
RoundCreator/Template.py
RoundCreator/__init__.py
RoundCreator.egg-info/PKG-INFO
RoundCreator.egg-info/SOURCES.txt
RoundCreator.egg-info/dependency_links.txt
RoundCreator.egg-info/entry_points.txt
RoundCreator.egg-info/top_level.txt